windmill_lib/__init__.py
windmill_lib/event_bus.py
windmill_lib/models.py
windmill_lib-0.0.4.dist-info/METADATA
windmill_lib-0.0.4.dist-info/WHEEL
windmill_lib-0.0.4.dist-info/licenses/LICENSE
windmill_lib-0.0.4.dist-info/RECORD
