Metadata-Version: 2.4
Name: windmill_lib
Version: 0.0.4
Summary: A tiny library that offers support for event handling and messaging streams between multiple consumers.
Project-URL: homepage, https://github.com/abdielsouza/windmill
Project-URL: repository, https://github.com/abdielsouza/windmill
Author-email: Abdiel Souza <abdielcsouza@gmail.com>
License-Expression: MIT
License-File: LICENSE
Requires-Python: >=3.10
